nonebot_plugin_vocu/__init__.py
nonebot_plugin_vocu/config.py
nonebot_plugin_vocu/vocu.py
nonebot_plugin_vocu-0.3.2.dist-info/licenses/LICENSE
nonebot_plugin_vocu-0.3.2.dist-info/METADATA
nonebot_plugin_vocu-0.3.2.dist-info/WHEEL
nonebot_plugin_vocu-0.3.2.dist-info/top_level.txt
nonebot_plugin_vocu-0.3.2.dist-info/RECORD
