Metadata-Version: 2.4
Name: nonebot-plugin-vocu
Version: 0.3.2
Summary: nonebot2 onebot v11 Vocu 语音插件
Author-email: fllesser <fllessive@gmail.com>
Requires-Python: <3.13,>=3.10
License-File: LICENSE
Requires-Dist: aiohttp<4.0.0,>=3.10.0
Requires-Dist: tqdm<5.0.0,>=4.67.1
Requires-Dist: aiofiles>=24.1.0
Requires-Dist: nonebot2<3.0.0,>=2.4.2
Requires-Dist: nonebot-adapter-onebot<3.0.0,>=2.4.6
Requires-Dist: nonebot-plugin-localstore<1.0.0,>=0.7.4
Dynamic: license-file
